brainscore_vision/__init__.py
brainscore_vision/__main__.py
brainscore_vision/model_interface.py
brainscore_vision/benchmark_helpers/__init__.py
brainscore_vision/benchmark_helpers/neural_common.py
brainscore_vision/benchmark_helpers/properties_common.py
brainscore_vision/benchmark_helpers/screen.py
brainscore_vision/benchmark_helpers/test_helper.py
brainscore_vision/benchmarks/README.md
brainscore_vision/benchmarks/__init__.py
brainscore_vision/benchmarks/baker2022/__init__.py
brainscore_vision/benchmarks/baker2022/benchmark.py
brainscore_vision/benchmarks/baker2022/requirements.txt
brainscore_vision/benchmarks/baker2022/test.py
brainscore_vision/benchmarks/bmd2024/__init__.py
brainscore_vision/benchmarks/bmd2024/benchmark.py
brainscore_vision/benchmarks/bmd2024/test.py
brainscore_vision/benchmarks/bracci2019/__init__.py
brainscore_vision/benchmarks/bracci2019/benchmark.py
brainscore_vision/benchmarks/bracci2019/requirements.txt
brainscore_vision/benchmarks/cadena2017/__init__.py
brainscore_vision/benchmarks/cadena2017/benchmark.py
brainscore_vision/benchmarks/cadena2017/test.py
brainscore_vision/benchmarks/coggan2024_behavior/__init__.py
brainscore_vision/benchmarks/coggan2024_behavior/benchmark.py
brainscore_vision/benchmarks/coggan2024_behavior/test.py
brainscore_vision/benchmarks/coggan2024_fMRI/__init__.py
brainscore_vision/benchmarks/coggan2024_fMRI/benchmark.py
brainscore_vision/benchmarks/coggan2024_fMRI/test.py
brainscore_vision/benchmarks/ferguson2024/__init__.py
brainscore_vision/benchmarks/ferguson2024/benchmark.py
brainscore_vision/benchmarks/ferguson2024/requirements.txt
brainscore_vision/benchmarks/ferguson2024/test.py
brainscore_vision/benchmarks/ferguson2024/helpers/helpers.py
brainscore_vision/benchmarks/freemanziemba2013/__init__.py
brainscore_vision/benchmarks/freemanziemba2013/test.py
brainscore_vision/benchmarks/freemanziemba2013/benchmarks/benchmark.py
brainscore_vision/benchmarks/freemanziemba2013/benchmarks/public_benchmarks.py
brainscore_vision-2.2.4.dist-info/LICENSE
brainscore_vision-2.2.4.dist-info/METADATA
brainscore_vision-2.2.4.dist-info/WHEEL
brainscore_vision-2.2.4.dist-info/top_level.txt
brainscore_vision-2.2.4.dist-info/RECORD
