Metadata-Version: 2.1
Name: brainscore_vision
Version: 2.2.4
Summary: The Brain-Score library enables model comparisons to behavioral and neural experiments
License: 
Requires-Python: >=3.11
License-File: LICENSE
Requires-Dist: numpy<2
Requires-Dist: brainscore-core
Requires-Dist: result-caching
Requires-Dist: importlib-metadata<5
Requires-Dist: scikit-learn
Requires-Dist: scipy
Requires-Dist: opencv-python
Requires-Dist: h5py
Requires-Dist: tqdm
Requires-Dist: gitpython
Requires-Dist: fire
Requires-Dist: jupyter
Requires-Dist: pybtex
Requires-Dist: peewee
Requires-Dist: psycopg2-binary
Requires-Dist: networkx
Requires-Dist: eva-decord
Requires-Dist: psutil
Provides-Extra: test
Requires-Dist: pytest; extra == "test"
Requires-Dist: pytest_check; extra == "test"
Requires-Dist: pytest-mock; extra == "test"
Requires-Dist: pytest-timeout; extra == "test"
Requires-Dist: torch; extra == "test"
Requires-Dist: torchvision; extra == "test"
Requires-Dist: matplotlib; extra == "test"
Requires-Dist: pytest-mock; extra == "test"
